<magics>
<class action="pmetgram" directory="visualisers" prefix="metgram" xmltag="metgraph" name="MetgramBar">
<!--
(C) Copyright 1996-2016 ECMWF.

This software is licensed under the terms of the Apache Licence Version 2.0
which can be obtained at http://www.apache.org/licenses/LICENSE-2.0. 
In applying this licence, ECMWF does not waive the privileges and immunities 
granted to it by virtue of its status as an intergovernmental organisation nor
does it submit to any jurisdiction.
-->

    	<documentation>
        The metgram curve will plot the metgram a s a curve! 
    	</documentation>
        	
        	<parameter member="keyword" to="string" default="curve1" from="string" name="metgram_bar_keyword">           
            		<documentation> keyword used for define the bars	</documentation>
        	</parameter>
        	
        	<parameter member="colour" to="Colour" default="blue" from="string" name="metgram_bar_colour">           
            		<documentation> Colour of the curve  		</documentation>
        	</parameter>
        	
         	
</class>
</magics>
